MANIFEST.in
README.rst
setup.py
igor/__init__.py
igor/algo.py
igor/batching.py
igor/cache.py
igor/enum.py
igor/fieldspec.py
igor/jsutil.py
igor/plugins.py
igor/serialize.py
igor/string.py
igor/traits.py
igor/appengine/__init__.py
igor/appengine/rcon.py
igor/appengine/tasks.py
igor/appengine/util.py
igor/djangoutil/__init__.py
igor/djangoutil/api.py
igor/djangoutil/auth.py
igor/djangoutil/db.py
igor/djangoutil/http.py
igor/djangoutil/util.py
igor/djangoutil/views.py
igor/djangoutil/fields/__init__.py
igor/djangoutil/fields/bzjsonfield.py
igor/djangoutil/fields/jsfield.py
igor/djangoutil/fields/jsonfield.py
igor/util/__init__.py
igor/util/batching.py
igor/util/fngroup.py
igor/util/pagecache.py
igor/util/pystack.py
igor/util/quickapp.py
igor/util/rst.py
igor/util/simplewsgi.py
igor/util/time.py
libigor.egg-info/PKG-INFO
libigor.egg-info/SOURCES.txt
libigor.egg-info/dependency_links.txt
libigor.egg-info/requires.txt
libigor.egg-info/top_level.txt
tests/test_fieldspec.py
tests/test_fngroup.py
tests/test_serialization.py