Metadata-Version: 1.1
Name: libigor
Version: 0.6.8
Summary: Collection of general purpose python libraries with focus on web development
Home-page: http://github.com/novopl/igor
Author: Mateusz 'novo' Klos
Author-email: novopl@gmail.com
License: MIT
Keywords: webdev web framework jsobj serialize utility
Platform: UNKNOWN
Classifier: Development Status :: 4 - Beta
Classifier: Topic :: Utilities
Classifier: Intended Audience :: Developers
Classifier: Programming Language :: Python
Classifier: License :: OSI Approved :: MIT License
